keras_toolbox-0.1.2.dist-info/DESCRIPTION.rst
keras_toolbox-0.1.2.dist-info/METADATA
keras_toolbox-0.1.2.dist-info/RECORD
keras_toolbox-0.1.2.dist-info/WHEEL
keras_toolbox-0.1.2.dist-info/metadata.json
keras_toolbox-0.1.2.dist-info/top_level.txt
kerastoolbox/__init__.py
kerastoolbox/augmentation.py
kerastoolbox/callbacks.py
kerastoolbox/io.py
kerastoolbox/utils.py
kerastoolbox/visu.py
