Metadata-Version: 2.0
Name: keras-toolbox
Version: 0.1.2
Summary: Everyday toolbox for Keras
Home-page: https://github.com/hadim/keras-toolbox
Author: Hadrien Mary
Author-email: hadrien.mary@gmail.com
License: MIT
Download-URL: https://github.com/hadim/keras-toolbox/archive/master.zip
Platform: UNKNOWN
